dbdm/__init__.py
dbdm/common.py
dbdm/cwtch.py
dbdm/pydantic.py
dbdm-0.1.0.dist-info/LICENSE
dbdm-0.1.0.dist-info/METADATA
dbdm-0.1.0.dist-info/WHEEL
dbdm-0.1.0.dist-info/RECORD
