Metadata-Version: 2.1
Name: dbdm
Version: 0.1.0
Summary: 
License: MIT
Author: Roman Koshel
Author-email: roma.koshel@gmail.com
Requires-Python: >=3.11,<4.0
Classifier: Development Status :: 3 - Alpha
Classifier: License :: OSI Approved :: MIT License
Classifier: Programming Language :: Python
Classifier: Programming Language :: Python :: 3
Classifier: Programming Language :: Python :: 3.11
Classifier: Programming Language :: Python :: 3.12
Classifier: Programming Language :: Python :: 3.13
Classifier: Programming Language :: Python :: 3 :: Only
Classifier: Topic :: Software Development :: Libraries :: Python Modules
Classifier: Topic :: Utilities
Requires-Dist: asyncpg
Requires-Dist: sqlalchemy[asyncio] (>=2,<3)
